sctour/__init__.py
sctour/_utils.py
sctour/data.py
sctour/logger.py
sctour/model.py
sctour/module.py
sctour/predict.py
sctour/train.py
sctour/vector_field.py
sctour-1.0.0.dist-info/LICENSE
sctour-1.0.0.dist-info/METADATA
sctour-1.0.0.dist-info/WHEEL
sctour-1.0.0.dist-info/top_level.txt
sctour-1.0.0.dist-info/RECORD
