Metadata-Version: 2.1
Name: sctour
Version: 1.0.0
Summary: a deep learning architecture for robust inference and accurate prediction of cellular dynamics
Home-page: https://github.com/LiQian-XC/sctour
Author: Qian Li
Author-email: liqian.picb@gmail.com
License: UNKNOWN
Platform: UNKNOWN
Classifier: Programming Language :: Python :: 3
Classifier: Operating System :: OS Independent
Classifier: Intended Audience :: Science/Research
Classifier: Topic :: Scientific/Engineering :: Bio-Informatics
Classifier: Development Status :: 4 - Beta
Requires-Python: >=3.7
Requires-Dist: torch (>=1.9.1)
Requires-Dist: torchdiffeq (>=0.2.2)
Requires-Dist: numpy (>=1.19.2)
Requires-Dist: scanpy (>=1.7.1)
Requires-Dist: anndata (>=0.7.5)
Requires-Dist: scipy (>=1.5.2)
Requires-Dist: tqdm (>=4.32.2)
Requires-Dist: scikit-learn (>=0.24.1)
Requires-Dist: leidenalg (>=0.8.4)
